[
  {
    "english": "General Secretary",
    "vietnamese": "Bí thư"
  },
  {
    "english": "captain (n)",
    "vietnamese": "đội trưởng"
  },
  {
    "english": "feat (n)",
    "vietnamese": "chiến công"
  },
  {
    "english": "military general",
    "vietnamese": "tướng quân đội"
  },
  {
    "english": "armored vehicles",
    "vietnamese": "xe bọc thép"
  },
  {
    "english": "Minister (n)",
    "vietnamese": "Bộ trưởng"
  },
  {
    "english": "tank (n)",
    "vietnamese": "xe tăng"
  },
  {
    "english": "Foreign Affairs",
    "vietnamese": "Bộ ngoại giao"
  },
  {
    "english": "disrupt (v)",
    "vietnamese": "phá hủy"
  },
  {
    "english": "memoir (n)",
    "vietnamese": "hồi ký"
  },
  {
    "english": "weapon depot",
    "vietnamese": "kho vũ khí"
  },
  {
    "english": "gratitude (n)",
    "vietnamese": "lòng biết ơn"
  },
  {
    "english": "comrade (n)",
    "vietnamese": "đồng đội"
  },
  {
    "english": "fellow citizen",
    "vietnamese": "bạn bè"
  },
  {
    "english": "Communist Youth Union",
    "vietnamese": "Đoàn thanh niên Cộng sản"
  },
  {
    "english": "Pioneers’s Organization",
    "vietnamese": "Đội thiếu niên tiền phong"
  }
]
